langevals_lingua/language_detection.py
langevals_lingua-0.1.12.dist-info/METADATA
langevals_lingua-0.1.12.dist-info/WHEEL
langevals_lingua-0.1.12.dist-info/RECORD
